<?xml version="1.0" encoding="utf-8"?>
<clothing-items>
 <clothing>
  <id>
   926616429
  </id>
  <name>
   Adidas Jeans Y-8304
  </name>
  <category>
   Jeans
  </category>
  <size>
   M
  </size>
  <color>
   Желтый
  </color>
  <material>
   Вискоза
  </material>
  <price>
   836504
  </price>
  <rating>
   4.21
  </rating>
  <reviews>
   809740
  </reviews>
  <new>
   -
  </new>
  <exclusive>
   no
  </exclusive>
 </clothing>
 <clothing>
  <id>
   140549468
  </id>
  <name>
   Asics Skirt D-9818
  </name>
  <category>
   Skirt
  </category>
  <size>
   S
  </size>
  <color>
   Зеленый
  </color>
  <material>
   Полиэстер
  </material>
  <price>
   673163
  </price>
  <rating>
   1.47
  </rating>
  <reviews>
   493214
  </reviews>
  <new>
   +
  </new>
  <sporty>
   no
  </sporty>
 </clothing>
 <clothing>
  <id>
   349335273
  </id>
  <name>
   Puma Umbrellas U-4521
  </name>
  <category>
   Umbrellas
  </category>
  <size>
   XXL
  </size>
  <color>
   Желтый
  </color>
  <material>
   Лен
  </material>
  <price>
   891673
  </price>
  <rating>
   4.72
  </rating>
  <reviews>
   365095
  </reviews>
  <exclusive>
   yes
  </exclusive>
  <sporty>
   yes
  </sporty>
 </clothing>
 <clothing>
  <id>
   894621051
  </id>
  <name>
   Brooks Blouse B-9743
  </name>
  <category>
   Blouse
  </category>
  <size>
   XXL
  </size>
  <color>
   Желтый
  </color>
  <material>
   Кожа
  </material>
  <price>
   836238
  </price>
  <rating>
   2.74
  </rating>
  <reviews>
   897875
  </reviews>
  <new>
   -
  </new>
 </clothing>
 <clothing>
  <id>
   314095903
  </id>
  <name>
   Fila Blouse U-2935
  </name>
  <category>
   Blouse
  </category>
  <size>
   XL
  </size>
  <color>
   Зеленый
  </color>
  <material>
   Кожа
  </material>
  <price>
   351905
  </price>
  <rating>
   2.75
  </rating>
  <reviews>
   48675
  </reviews>
  <exclusive>
   no
  </exclusive>
  <sporty>
   no
  </sporty>
 </clothing>
 <clothing>
  <id>
   360535825
  </id>
  <name>
   Nike Hat M-1437
  </name>
  <category>
   Hat
  </category>
  <size>
   S
  </size>
  <color>
   Фиолетовый
  </color>
  <material>
   Нейлон
  </material>
  <price>
   380376
  </price>
  <rating>
   1.97
  </rating>
  <reviews>
   2960
  </reviews>
  <exclusive>
   yes
  </exclusive>
  <sporty>
   yes
  </sporty>
 </clothing>
 <clothing>
  <id>
   474881403
  </id>
  <name>
   Brooks Skirt H-7633
  </name>
  <category>
   Skirt
  </category>
  <size>
   XL
  </size>
  <color>
   Оранжевый
  </color>
  <material>
   Вискоза
  </material>
  <price>
   966376
  </price>
  <rating>
   4.12
  </rating>
  <reviews>
   362459
  </reviews>
  <exclusive>
   no
  </exclusive>
  <sporty>
   yes
  </sporty>
 </clothing>
 <clothing>
  <id>
   735849343
  </id>
  <name>
   Ellesse Handbags U-7739
  </name>
  <category>
   Handbags
  </category>
  <size>
   M
  </size>
  <color>
   Красный
  </color>
  <material>
   Хлопок
  </material>
  <price>
   106694
  </price>
  <rating>
   4.93
  </rating>
  <reviews>
   669171
  </reviews>
  <new>
   +
  </new>
  <sporty>
   yes
  </sporty>
 </clothing>
 <clothing>
  <id>
   410262535
  </id>
  <name>
   Reebok Shoes E-5253
  </name>
  <category>
   Shoes
  </category>
  <size>
   XXL
  </size>
  <color>
   Фиолетовый
  </color>
  <material>
   Лен
  </material>
  <price>
   193708
  </price>
  <rating>
   4.21
  </rating>
  <reviews>
   613482
  </reviews>
  <new>
   +
  </new>
  <exclusive>
   no
  </exclusive>
  <sporty>
   no
  </sporty>
 </clothing>
 <clothing>
  <id>
   372525332
  </id>
  <name>
   Addidas Shirt N-1640
  </name>
  <category>
   Shirt
  </category>
  <size>
   S
  </size>
  <color>
   Зеленый
  </color>
  <material>
   Полиэстер
  </material>
  <price>
   323434
  </price>
  <rating>
   2.76
  </rating>
  <reviews>
   856659
  </reviews>
  <new>
   +
  </new>
  <exclusive>
   no
  </exclusive>
 </clothing>
 <clothing>
  <id>
   243717084
  </id>
  <name>
   Lacoste Shirt P-8417
  </name>
  <category>
   Shirt
  </category>
  <size>
   XXL
  </size>
  <color>
   Голубой
  </color>
  <material>
   Полиэстер
  </material>
  <price>
   788987
  </price>
  <rating>
   2.07
  </rating>
  <reviews>
   677694
  </reviews>
 </clothing>
 <clothing>
  <id>
   839739395
  </id>
  <name>
   Brooks Belts K-5001
  </name>
  <category>
   Belts
  </category>
  <size>
   XXL
  </size>
  <color>
   Желтый
  </color>
  <material>
   Полиэстер
  </material>
  <price>
   739662
  </price>
  <rating>
   4.67
  </rating>
  <reviews>
   808662
  </reviews>
  <new>
   -
  </new>
  <exclusive>
   yes
  </exclusive>
  <sporty>
   yes
  </sporty>
 </clothing>
 <clothing>
  <id>
   381891949
  </id>
  <name>
   Puma Gloves U-6078
  </name>
  <category>
   Gloves
  </category>
  <size>
   XXL
  </size>
  <color>
   Голубой
  </color>
  <material>
   Шерсть
  </material>
  <price>
   512964
  </price>
  <rating>
   1.01
  </rating>
  <reviews>
   34693
  </reviews>
  <new>
   -
  </new>
  <exclusive>
   no
  </exclusive>
 </clothing>
 <clothing>
  <id>
   471833250
  </id>
  <name>
   Under Armour T-shirt S-6448
  </name>
  <category>
   T-shirt
  </category>
  <size>
   XL
  </size>
  <color>
   Синий
  </color>
  <material>
   Вискоза
  </material>
  <price>
   973775
  </price>
  <rating>
   4.77
  </rating>
  <reviews>
   588639
  </reviews>
  <new>
   -
  </new>
  <exclusive>
   yes
  </exclusive>
 </clothing>
 <clothing>
  <id>
   250241958
  </id>
  <name>
   Nike Shoes S-4220
  </name>
  <category>
   Shoes
  </category>
  <size>
   XXL
  </size>
  <color>
   Синий
  </color>
  <material>
   Кожа
  </material>
  <price>
   830406
  </price>
  <rating>
   2.01
  </rating>
  <reviews>
   231244
  </reviews>
  <new>
   +
  </new>
  <exclusive>
   yes
  </exclusive>
  <sporty>
   no
  </sporty>
 </clothing>
 <clothing>
  <id>
   308284094
  </id>
  <name>
   Addidas Pants W-3518
  </name>
  <category>
   Pants
  </category>
  <size>
   S
  </size>
  <color>
   Желтый
  </color>
  <material>
   Шерсть
  </material>
  <price>
   365670
  </price>
  <rating>
   2.39
  </rating>
  <reviews>
   138305
  </reviews>
  <new>
   +
  </new>
  <exclusive>
   yes
  </exclusive>
 </clothing>
 <clothing>
  <id>
   445708922
  </id>
  <name>
   Puma Jeans E-4850
  </name>
  <category>
   Jeans
  </category>
  <size>
   L
  </size>
  <color>
   Зеленый
  </color>
  <material>
   Шерсть
  </material>
  <price>
   751971
  </price>
  <rating>
   2.59
  </rating>
  <reviews>
   657990
  </reviews>
  <new>
   -
  </new>
 </clothing>
 <clothing>
  <id>
   974670058
  </id>
  <name>
   Converse Socks N-6342
  </name>
  <category>
   Socks
  </category>
  <size>
   L
  </size>
  <color>
   Оранжевый
  </color>
  <material>
   Хлопок
  </material>
  <price>
   949347
  </price>
  <rating>
   1.54
  </rating>
  <reviews>
   353059
  </reviews>
  <exclusive>
   no
  </exclusive>
  <sporty>
   yes
  </sporty>
 </clothing>
 <clothing>
  <id>
   640078662
  </id>
  <name>
   Reebok Hat R-1802
  </name>
  <category>
   Hat
  </category>
  <size>
   L
  </size>
  <color>
   Зеленый
  </color>
  <material>
   Вискоза
  </material>
  <price>
   790894
  </price>
  <rating>
   3.07
  </rating>
  <reviews>
   552799
  </reviews>
 </clothing>
 <clothing>
  <id>
   418393692
  </id>
  <name>
   PleinSport T-shirt A-6903
  </name>
  <category>
   T-shirt
  </category>
  <size>
   XXL
  </size>
  <color>
   Желтый
  </color>
  <material>
   Вискоза
  </material>
  <price>
   512933
  </price>
  <rating>
   4.35
  </rating>
  <reviews>
   893912
  </reviews>
  <new>
   -
  </new>
  <sporty>
   no
  </sporty>
 </clothing>
 <clothing>
  <id>
   619155872
  </id>
  <name>
   Addidas Skirt C-9231
  </name>
  <category>
   Skirt
  </category>
  <size>
   M
  </size>
  <color>
   Желтый
  </color>
  <material>
   Лен
  </material>
  <price>
   263635
  </price>
  <rating>
   4.31
  </rating>
  <reviews>
   511343
  </reviews>
  <new>
   -
  </new>
  <exclusive>
   yes
  </exclusive>
 </clothing>
 <clothing>
  <id>
   397399119
  </id>
  <name>
   DC Shirt D-7177
  </name>
  <category>
   Shirt
  </category>
  <size>
   M
  </size>
  <color>
   Фиолетовый
  </color>
  <material>
   Хлопок
  </material>
  <price>
   720310
  </price>
  <rating>
   4.46
  </rating>
  <reviews>
   379941
  </reviews>
  <new>
   -
  </new>
  <exclusive>
   yes
  </exclusive>
 </clothing>
 <clothing>
  <id>
   975964039
  </id>
  <name>
   Adidas T-shirt Z-6291
  </name>
  <category>
   T-shirt
  </category>
  <size>
   M
  </size>
  <color>
   Фиолетовый
  </color>
  <material>
   Кожа
  </material>
  <price>
   117179
  </price>
  <rating>
   2.84
  </rating>
  <reviews>
   7718
  </reviews>
  <sporty>
   yes
  </sporty>
 </clothing>
 <clothing>
  <id>
   531323316
  </id>
  <name>
   Vans Gloves Z-8290
  </name>
  <category>
   Gloves
  </category>
  <size>
   S
  </size>
  <color>
   Красный
  </color>
  <material>
   Вискоза
  </material>
  <price>
   240888
  </price>
  <rating>
   2.54
  </rating>
  <reviews>
   28805
  </reviews>
  <new>
   +
  </new>
  <exclusive>
   yes
  </exclusive>
  <sporty>
   no
  </sporty>
 </clothing>
 <clothing>
  <id>
   653544072
  </id>
  <name>
   Vans Hat X-9437
  </name>
  <category>
   Hat
  </category>
  <size>
   XL
  </size>
  <color>
   Красный
  </color>
  <material>
   Шелк
  </material>
  <price>
   648587
  </price>
  <rating>
   1.05
  </rating>
  <reviews>
   548685
  </reviews>
  <exclusive>
   no
  </exclusive>
 </clothing>
 <clothing>
  <id>
   266343100
  </id>
  <name>
   PleinSport Shirt Q-8135
  </name>
  <category>
   Shirt
  </category>
  <size>
   XXL
  </size>
  <color>
   Зеленый
  </color>
  <material>
   Шерсть
  </material>
  <price>
   818788
  </price>
  <rating>
   1.34
  </rating>
  <reviews>
   844511
  </reviews>
  <new>
   -
  </new>
 </clothing>
 <clothing>
  <id>
   218037484
  </id>
  <name>
   Vans Belts U-5353
  </name>
  <category>
   Belts
  </category>
  <size>
   M
  </size>
  <color>
   Красный
  </color>
  <material>
   Шелк
  </material>
  <price>
   172088
  </price>
  <rating>
   3.12
  </rating>
  <reviews>
   664541
  </reviews>
  <new>
   -
  </new>
  <exclusive>
   no
  </exclusive>
  <sporty>
   no
  </sporty>
 </clothing>
 <clothing>
  <id>
   864475274
  </id>
  <name>
   Vans Shoes P-4826
  </name>
  <category>
   Shoes
  </category>
  <size>
   XXL
  </size>
  <color>
   Фиолетовый
  </color>
  <material>
   Нейлон
  </material>
  <price>
   732409
  </price>
  <rating>
   1.4
  </rating>
  <reviews>
   486217
  </reviews>
  <exclusive>
   no
  </exclusive>
  <sporty>
   yes
  </sporty>
 </clothing>
 <clothing>
  <id>
   124178246
  </id>
  <name>
   New Balance Skirt H-8035
  </name>
  <category>
   Skirt
  </category>
  <size>
   XL
  </size>
  <color>
   Желтый
  </color>
  <material>
   Вискоза
  </material>
  <price>
   969170
  </price>
  <rating>
   3.12
  </rating>
  <reviews>
   265887
  </reviews>
 </clothing>
</clothing-items>
