<?xml version="1.0" encoding="utf-8"?>
<clothing-items>
 <clothing>
  <id>
   582655925
  </id>
  <name>
   Addidas Jacket F-8884
  </name>
  <category>
   Jacket
  </category>
  <size>
   S
  </size>
  <color>
   Голубой
  </color>
  <material>
   Лен
  </material>
  <price>
   709651
  </price>
  <rating>
   3.61
  </rating>
  <reviews>
   894391
  </reviews>
  <exclusive>
   yes
  </exclusive>
 </clothing>
 <clothing>
  <id>
   923972743
  </id>
  <name>
   PleinSport Umbrellas F-2497
  </name>
  <category>
   Umbrellas
  </category>
  <size>
   S
  </size>
  <color>
   Зеленый
  </color>
  <material>
   Хлопок
  </material>
  <price>
   636123
  </price>
  <rating>
   1.58
  </rating>
  <reviews>
   254234
  </reviews>
  <new>
   +
  </new>
  <exclusive>
   yes
  </exclusive>
 </clothing>
 <clothing>
  <id>
   262679056
  </id>
  <name>
   Nike Jeans K-2015
  </name>
  <category>
   Jeans
  </category>
  <size>
   S
  </size>
  <color>
   Синий
  </color>
  <material>
   Вискоза
  </material>
  <price>
   808814
  </price>
  <rating>
   3.73
  </rating>
  <reviews>
   868551
  </reviews>
  <new>
   -
  </new>
  <exclusive>
   no
  </exclusive>
  <sporty>
   yes
  </sporty>
 </clothing>
 <clothing>
  <id>
   782256475
  </id>
  <name>
   Converse Umbrellas K-4821
  </name>
  <category>
   Umbrellas
  </category>
  <size>
   M
  </size>
  <color>
   Фиолетовый
  </color>
  <material>
   Нейлон
  </material>
  <price>
   578455
  </price>
  <rating>
   4.75
  </rating>
  <reviews>
   94497
  </reviews>
  <exclusive>
   no
  </exclusive>
 </clothing>
 <clothing>
  <id>
   988027334
  </id>
  <name>
   Puma Hat N-6380
  </name>
  <category>
   Hat
  </category>
  <size>
   L
  </size>
  <color>
   Фиолетовый
  </color>
  <material>
   Хлопок
  </material>
  <price>
   876714
  </price>
  <rating>
   4.42
  </rating>
  <reviews>
   950240
  </reviews>
  <new>
   +
  </new>
  <exclusive>
   yes
  </exclusive>
  <sporty>
   no
  </sporty>
 </clothing>
 <clothing>
  <id>
   536107427
  </id>
  <name>
   Ellesse Umbrellas W-2241
  </name>
  <category>
   Umbrellas
  </category>
  <size>
   S
  </size>
  <color>
   Фиолетовый
  </color>
  <material>
   Нейлон
  </material>
  <price>
   189843
  </price>
  <rating>
   4.85
  </rating>
  <reviews>
   820469
  </reviews>
 </clothing>
 <clothing>
  <id>
   589161994
  </id>
  <name>
   PleinSport Handbags W-8504
  </name>
  <category>
   Handbags
  </category>
  <size>
   M
  </size>
  <color>
   Оранжевый
  </color>
  <material>
   Шелк
  </material>
  <price>
   250590
  </price>
  <rating>
   3.31
  </rating>
  <reviews>
   929702
  </reviews>
  <new>
   +
  </new>
  <sporty>
   yes
  </sporty>
 </clothing>
 <clothing>
  <id>
   404427873
  </id>
  <name>
   Reebok Handbags S-8674
  </name>
  <category>
   Handbags
  </category>
  <size>
   L
  </size>
  <color>
   Оранжевый
  </color>
  <material>
   Лен
  </material>
  <price>
   123345
  </price>
  <rating>
   4.02
  </rating>
  <reviews>
   315238
  </reviews>
  <new>
   -
  </new>
  <exclusive>
   no
  </exclusive>
 </clothing>
 <clothing>
  <id>
   263311171
  </id>
  <name>
   Vans Jacket M-3030
  </name>
  <category>
   Jacket
  </category>
  <size>
   S
  </size>
  <color>
   Голубой
  </color>
  <material>
   Шерсть
  </material>
  <price>
   523620
  </price>
  <rating>
   3.98
  </rating>
  <reviews>
   209745
  </reviews>
  <new>
   +
  </new>
  <exclusive>
   yes
  </exclusive>
 </clothing>
 <clothing>
  <id>
   657711491
  </id>
  <name>
   Puma Jeans S-9142
  </name>
  <category>
   Jeans
  </category>
  <size>
   XL
  </size>
  <color>
   Синий
  </color>
  <material>
   Полиэстер
  </material>
  <price>
   955687
  </price>
  <rating>
   1.35
  </rating>
  <reviews>
   81782
  </reviews>
  <new>
   +
  </new>
 </clothing>
 <clothing>
  <id>
   317305652
  </id>
  <name>
   Lacoste Sweater S-8934
  </name>
  <category>
   Sweater
  </category>
  <size>
   S
  </size>
  <color>
   Голубой
  </color>
  <material>
   Шелк
  </material>
  <price>
   774341
  </price>
  <rating>
   3.83
  </rating>
  <reviews>
   442167
  </reviews>
  <new>
   +
  </new>
  <exclusive>
   yes
  </exclusive>
 </clothing>
 <clothing>
  <id>
   745221371
  </id>
  <name>
   Vans Skirt W-9945
  </name>
  <category>
   Skirt
  </category>
  <size>
   L
  </size>
  <color>
   Оранжевый
  </color>
  <material>
   Хлопок
  </material>
  <price>
   420801
  </price>
  <rating>
   1.28
  </rating>
  <reviews>
   256443
  </reviews>
  <new>
   +
  </new>
  <sporty>
   no
  </sporty>
 </clothing>
 <clothing>
  <id>
   162632936
  </id>
  <name>
   Under Armour Skirt U-7812
  </name>
  <category>
   Skirt
  </category>
  <size>
   M
  </size>
  <color>
   Зеленый
  </color>
  <material>
   Шелк
  </material>
  <price>
   407066
  </price>
  <rating>
   3.54
  </rating>
  <reviews>
   368830
  </reviews>
  <new>
   -
  </new>
  <sporty>
   no
  </sporty>
 </clothing>
 <clothing>
  <id>
   831855521
  </id>
  <name>
   Ellesse Blouse I-9475
  </name>
  <category>
   Blouse
  </category>
  <size>
   S
  </size>
  <color>
   Синий
  </color>
  <material>
   Шерсть
  </material>
  <price>
   142133
  </price>
  <rating>
   4.85
  </rating>
  <reviews>
   67561
  </reviews>
  <new>
   -
  </new>
  <exclusive>
   yes
  </exclusive>
 </clothing>
 <clothing>
  <id>
   143761547
  </id>
  <name>
   Brooks Skirt Z-5145
  </name>
  <category>
   Skirt
  </category>
  <size>
   XXL
  </size>
  <color>
   Фиолетовый
  </color>
  <material>
   Лен
  </material>
  <price>
   781101
  </price>
  <rating>
   3.86
  </rating>
  <reviews>
   493315
  </reviews>
  <new>
   +
  </new>
  <exclusive>
   no
  </exclusive>
 </clothing>
 <clothing>
  <id>
   282847429
  </id>
  <name>
   Converse Handbags Q-3929
  </name>
  <category>
   Handbags
  </category>
  <size>
   XXL
  </size>
  <color>
   Голубой
  </color>
  <material>
   Кожа
  </material>
  <price>
   822370
  </price>
  <rating>
   2.64
  </rating>
  <reviews>
   603529
  </reviews>
  <new>
   -
  </new>
  <exclusive>
   no
  </exclusive>
  <sporty>
   no
  </sporty>
 </clothing>
 <clothing>
  <id>
   183771454
  </id>
  <name>
   Reebok Pants P-8703
  </name>
  <category>
   Pants
  </category>
  <size>
   XXL
  </size>
  <color>
   Синий
  </color>
  <material>
   Кожа
  </material>
  <price>
   321844
  </price>
  <rating>
   1.0
  </rating>
  <reviews>
   655171
  </reviews>
  <new>
   +
  </new>
  <sporty>
   yes
  </sporty>
 </clothing>
 <clothing>
  <id>
   719371399
  </id>
  <name>
   New Balance Blouse C-6884
  </name>
  <category>
   Blouse
  </category>
  <size>
   XL
  </size>
  <color>
   Желтый
  </color>
  <material>
   Хлопок
  </material>
  <price>
   395529
  </price>
  <rating>
   1.71
  </rating>
  <reviews>
   675315
  </reviews>
  <exclusive>
   no
  </exclusive>
 </clothing>
 <clothing>
  <id>
   542430865
  </id>
  <name>
   Fila Handbags B-1316
  </name>
  <category>
   Handbags
  </category>
  <size>
   L
  </size>
  <color>
   Фиолетовый
  </color>
  <material>
   Лен
  </material>
  <price>
   766158
  </price>
  <rating>
   2.0
  </rating>
  <reviews>
   800163
  </reviews>
  <new>
   -
  </new>
  <exclusive>
   no
  </exclusive>
  <sporty>
   yes
  </sporty>
 </clothing>
 <clothing>
  <id>
   200461088
  </id>
  <name>
   Addidas Shirt R-6634
  </name>
  <category>
   Shirt
  </category>
  <size>
   L
  </size>
  <color>
   Красный
  </color>
  <material>
   Кожа
  </material>
  <price>
   387187
  </price>
  <rating>
   1.34
  </rating>
  <reviews>
   793142
  </reviews>
  <new>
   -
  </new>
  <exclusive>
   no
  </exclusive>
 </clothing>
 <clothing>
  <id>
   743193262
  </id>
  <name>
   Fila Jacket E-5333
  </name>
  <category>
   Jacket
  </category>
  <size>
   M
  </size>
  <color>
   Фиолетовый
  </color>
  <material>
   Лен
  </material>
  <price>
   720013
  </price>
  <rating>
   3.46
  </rating>
  <reviews>
   127389
  </reviews>
  <exclusive>
   no
  </exclusive>
  <sporty>
   no
  </sporty>
 </clothing>
 <clothing>
  <id>
   250604852
  </id>
  <name>
   Lacoste Pants V-4474
  </name>
  <category>
   Pants
  </category>
  <size>
   M
  </size>
  <color>
   Фиолетовый
  </color>
  <material>
   Шерсть
  </material>
  <price>
   852159
  </price>
  <rating>
   1.06
  </rating>
  <reviews>
   902600
  </reviews>
  <new>
   -
  </new>
 </clothing>
 <clothing>
  <id>
   179980737
  </id>
  <name>
   Adidas Shoes I-9502
  </name>
  <category>
   Shoes
  </category>
  <size>
   L
  </size>
  <color>
   Голубой
  </color>
  <material>
   Лен
  </material>
  <price>
   795282
  </price>
  <rating>
   1.24
  </rating>
  <reviews>
   666909
  </reviews>
  <new>
   -
  </new>
  <sporty>
   yes
  </sporty>
 </clothing>
 <clothing>
  <id>
   299578558
  </id>
  <name>
   Brooks Jeans R-6585
  </name>
  <category>
   Jeans
  </category>
  <size>
   L
  </size>
  <color>
   Зеленый
  </color>
  <material>
   Лен
  </material>
  <price>
   466898
  </price>
  <rating>
   1.38
  </rating>
  <reviews>
   113210
  </reviews>
  <sporty>
   yes
  </sporty>
 </clothing>
 <clothing>
  <id>
   118285974
  </id>
  <name>
   Nike Hat M-3850
  </name>
  <category>
   Hat
  </category>
  <size>
   M
  </size>
  <color>
   Фиолетовый
  </color>
  <material>
   Кожа
  </material>
  <price>
   602887
  </price>
  <rating>
   4.12
  </rating>
  <reviews>
   676635
  </reviews>
  <exclusive>
   no
  </exclusive>
 </clothing>
 <clothing>
  <id>
   486683456
  </id>
  <name>
   Nike Sweater M-5837
  </name>
  <category>
   Sweater
  </category>
  <size>
   XL
  </size>
  <color>
   Оранжевый
  </color>
  <material>
   Кожа
  </material>
  <price>
   602828
  </price>
  <rating>
   3.01
  </rating>
  <reviews>
   336571
  </reviews>
  <new>
   +
  </new>
  <sporty>
   no
  </sporty>
 </clothing>
</clothing-items>
